collect_pack/__init__.py
collect_pack/__main__.py
collect_pack/collect_framework.py
collect_pack/pack/__init__.py
collect_pack/pack/collect_framework.py
collect_pack-1.3.dist-info/METADATA
collect_pack-1.3.dist-info/WHEEL
collect_pack-1.3.dist-info/top_level.txt
collect_pack-1.3.dist-info/RECORD
