Metadata-Version: 2.1
Name: collect-pack
Version: 1.3
Summary: UNKNOWN
Home-page: UNKNOWN
Author: Anybody and No one
License: UNKNOWN
Platform: UNKNOWN
Requires-Dist: markdown
Requires-Dist: argparse
